{
	"class" : {
		"widgetClassIcon" : "mt 8/21/2012 10:14:45.977",
		"widgetClassName" : "mt 10/19/2010 14:05:23.132" },
	"instance" : {
		"acceptDroppingMorph:event:" : "mt 11/6/2012 13:21:27.938",
		"addChild:" : "mt 11/6/2012 16:20:15.724",
		"addPage" : "mt 11/6/2012 16:41:58.652",
		"addPage:" : "mt 5/8/2013 12:05:23.465",
		"addPageSilently:" : "mt 5/8/2013 12:05:07.125",
		"animatePageTurnFrom:to:" : "mt 3/6/2013 11:21:19.268",
		"animated" : "mt 11/7/2012 13:36:39.121",
		"animated:" : "mt 11/7/2012 13:36:29.526",
		"animationDirection" : "mt 6/28/2013 16:26:47.777",
		"animationDirection:" : "mt 6/28/2013 16:27:22.855",
		"animationDuration" : "mt 11/7/2012 16:30:06.518",
		"animationDuration:" : "mt 11/7/2012 16:29:50.785",
		"children" : "mt 11/6/2012 16:10:37.003",
		"clear" : "mt 11/7/2012 11:09:52.342",
		"click:" : "mt 10/23/2010 10:03:25.639",
		"currentIndex" : "mt 11/6/2012 11:50:20.162",
		"currentIndex:" : "mt 5/8/2013 13:37:54.273",
		"currentPage" : "mt 11/6/2012 11:50:41.168",
		"currentPageChanged" : "mt 6/27/2013 09:45:24.341",
		"editMode:" : "mt 7/5/2013 08:36:10.031",
		"initialize" : "mt 11/7/2012 15:10:28.942",
		"initializeEditButtons" : "mt 7/15/2013 08:31:06.19",
		"initializePages:startIndex:" : "mt 5/8/2013 12:06:05.716",
		"insertPage" : "mt 7/15/2013 08:32:27.017",
		"insertPage:behind:" : "mt 7/15/2013 08:30:26.969",
		"insertPage:inFrontOf:" : "mt 7/15/2013 08:30:22.386",
		"nextPage" : "mt 7/13/2010 10:15:59.084",
		"pages" : "mt 7/13/2010 09:36:45.708",
		"previousPage" : "mt 7/13/2010 10:16:13.279",
		"removeCurrentPage" : "mt 11/6/2012 13:27:38.867",
		"startDrag:" : "mt 7/13/2010 10:09:25.305",
		"updateCurrentPage" : "mt 6/27/2013 09:45:58.174",
		"updateCurrentPageSelection" : "mt 11/6/2012 13:11:08.697",
		"updateEditButtons" : "mt 11/6/2012 16:02:22.598",
		"updateSelfSelection" : "mt 11/6/2012 15:59:11.993" } }
