{
	"class" : {
		"bulletArrowDownSunkenIcon" : "mt 8/21/2012 09:48:45.709",
		"bulletArrowDownSunkenIconContents" : "mt 8/21/2012 09:44:41.359",
		"bulletArrowLeftSunkenIcon" : "mt 8/21/2012 09:49:02.52",
		"bulletArrowLeftSunkenIconContents" : "mt 8/21/2012 09:46:51.122",
		"bulletArrowRightSunkenIcon" : "mt 8/21/2012 09:49:10.076",
		"bulletArrowRightSunkenIconContents" : "mt 8/21/2012 09:46:34.98",
		"bulletArrowUpSunkenIcon" : "mt 8/21/2012 09:48:55.159",
		"bulletArrowUpSunkenIconContents" : "mt 8/21/2012 09:45:56.471",
		"crossSmallSunkenIcon" : "mt 8/21/2012 10:21:39.94",
		"crossSmallSunkenIconContents" : "mt 8/21/2012 10:20:31.193",
		"icon0418Small" : "mt 11/6/2012 15:56:48.704",
		"icon0418SmallContents" : "mt 11/6/2012 15:56:25.462",
		"initialize" : "mt 8/21/2012 09:55:39.318",
		"minusSmallIcon" : "mt 8/21/2012 10:30:10.046",
		"minusSmallIconContents" : "mt 8/21/2012 10:29:38.998",
		"plusSmallIcon" : "mt 8/21/2012 10:30:06.309",
		"plusSmallIconContents" : "mt 8/21/2012 10:29:22.486" },
	"instance" : {
		 } }
